odoo/addons/iot_oca/README.rst
odoo/addons/iot_oca/__init__.py
odoo/addons/iot_oca/__manifest__.py
odoo/addons/iot_oca/i18n/ca.po
odoo/addons/iot_oca/i18n/es.po
odoo/addons/iot_oca/i18n/fa.po
odoo/addons/iot_oca/i18n/fa_IR.po
odoo/addons/iot_oca/i18n/iot.pot
odoo/addons/iot_oca/i18n/iot_oca.pot
odoo/addons/iot_oca/i18n/it.po
odoo/addons/iot_oca/models/__init__.py
odoo/addons/iot_oca/models/iot_communication_system.py
odoo/addons/iot_oca/models/iot_communication_system_action.py
odoo/addons/iot_oca/models/iot_device.py
odoo/addons/iot_oca/models/iot_device_action.py
odoo/addons/iot_oca/models/iot_device_group.py
odoo/addons/iot_oca/models/iot_device_tag.py
odoo/addons/iot_oca/readme/CONTRIBUTORS.md
odoo/addons/iot_oca/readme/DESCRIPTION.md
odoo/addons/iot_oca/security/iot_security.xml
odoo/addons/iot_oca/security/ir.model.access.csv
odoo/addons/iot_oca/static/description/icon.png
odoo/addons/iot_oca/static/description/icon.svg
odoo/addons/iot_oca/static/description/index.html
odoo/addons/iot_oca/tests/__init__.py
odoo/addons/iot_oca/tests/test_iot.py
odoo/addons/iot_oca/views/iot_device_group.xml
odoo/addons/iot_oca/views/iot_device_tag.xml
odoo/addons/iot_oca/views/iot_device_views.xml
odoo/addons/iot_oca/views/iot_menu.xml
odoo/addons/iot_oca/views/iot_system_views.xml
odoo_addon_iot_oca-18.0.1.0.0.4.dist-info/METADATA
odoo_addon_iot_oca-18.0.1.0.0.4.dist-info/WHEEL
odoo_addon_iot_oca-18.0.1.0.0.4.dist-info/top_level.txt
odoo_addon_iot_oca-18.0.1.0.0.4.dist-info/RECORD
